<?xml version="1.0" encoding="UTF-8"?><record_update table="x_inthe_hr_case_mg_assignment_matrix">
    <x_inthe_hr_case_mg_assignment_matrix action="INSERT_OR_UPDATE">
        <sys_class_name>x_inthe_hr_case_mg_assignment_matrix</sys_class_name>
        <sys_created_by>tkaneko</sys_created_by>
        <sys_created_on>2018-01-12 17:53:20</sys_created_on>
        <sys_customer_update>false</sys_customer_update>
        <sys_id>a8686c3a4f6b0700af76d0af0310c705</sys_id>
        <sys_mod_count>1</sys_mod_count>
        <sys_name/>
        <sys_package display_value="HR Case Management" source="x_inthe_hr_case_mg">e048ecb04f2f3e00f5f3d49f0310c796</sys_package>
        <sys_policy/>
        <sys_replace_on_upgrade>false</sys_replace_on_upgrade>
        <sys_scope display_value="HR Case Management">e048ecb04f2f3e00f5f3d49f0310c796</sys_scope>
        <sys_update_name>x_inthe_hr_case_mg_assignment_matrix_a8686c3a4f6b0700af76d0af0310c705</sys_update_name>
        <sys_updated_by>tramos12</sys_updated_by>
        <sys_updated_on>2018-09-04 18:10:57</sys_updated_on>
        <u_active>false</u_active>
        <u_assignment_group/>
        <u_case_sub_type>On the Job Training</u_case_sub_type>
        <u_case_type>Education and Learning</u_case_type>
        <u_group_all_others display_value="My Learning" name="My Learning">75125c66136f834ce77d5cc12244b054</u_group_all_others>
        <u_group_executive display_value="My Learning" name="My Learning">75125c66136f834ce77d5cc12244b054</u_group_executive>
        <u_group_physician display_value="My Learning" name="My Learning">75125c66136f834ce77d5cc12244b054</u_group_physician>
        <u_organization/>
        <u_physician>false</u_physician>
    </x_inthe_hr_case_mg_assignment_matrix>
</record_update>
